dapr_agents/__init__.py
dapr_agents/py.typed
dapr_agents/agents/__init__.py
dapr_agents/agents/base.py
dapr_agents/agents/components.py
dapr_agents/agents/configs.py
dapr_agents/agents/durable.py
dapr_agents/agents/prompting.py
dapr_agents/agents/schemas.py
dapr_agents/agents/standalone.py
dapr_agents/agents/orchestrators/__init__.py
dapr_agents/agents/orchestrators/base.py
dapr_agents/agents/orchestrators/random.py
dapr_agents/agents/orchestrators/roundrobin.py
dapr_agents/agents/orchestrators/llm/__init__.py
dapr_agents/agents/orchestrators/llm/base.py
dapr_agents/agents/orchestrators/llm/configs.py
dapr_agents/agents/orchestrators/llm/orchestrator.py
dapr_agents/agents/orchestrators/llm/prompts.py
dapr_agents/agents/orchestrators/llm/schemas.py
dapr_agents/agents/orchestrators/llm/state.py
dapr_agents/agents/orchestrators/llm/utils.py
dapr_agents/agents/telemetry/__init__.py
dapr_agents/agents/telemetry/otel.py
dapr_agents/agents/utils/__init__.py
dapr_agents/agents/utils/auth.py
dapr_agents/agents/utils/message_converter.py
dapr_agents/agents/utils/text_printer.py
dapr_agents/document/__init__.py
dapr_agents/document/embedder/__init__.py
dapr_agents/document/embedder/base.py
dapr_agents/document/embedder/nvidia.py
dapr_agents/document/embedder/openai.py
dapr_agents/document/embedder/sentence.py
dapr_agents/document/fetcher/__init__.py
dapr_agents/document/fetcher/arxiv.py
dapr_agents/document/fetcher/base.py
dapr_agents/document/reader/__init__.py
dapr_agents/document/reader/base.py
dapr_agents/document/reader/text.py
dapr_agents/document/reader/pdf/__init__.py
dapr_agents/document/reader/pdf/pymupdf.py
dapr_agents/document/reader/pdf/pypdf.py
dapr_agents/document/splitter/__init__.py
dapr_agents/document/splitter/base.py
dapr_agents/document/splitter/text.py
dapr_agents/executors/__init__.py
dapr_agents/executors/base.py
dapr_agents/executors/docker.py
dapr_agents/executors/local.py
dapr_agents/executors/sandbox.py
dapr_agents-0.10.6.dist-info/licenses/LICENSE
dapr_agents-0.10.6.dist-info/METADATA
dapr_agents-0.10.6.dist-info/WHEEL
dapr_agents-0.10.6.dist-info/top_level.txt
dapr_agents-0.10.6.dist-info/RECORD
