Metadata-Version: 2.4
Name: dapr-agents
Version: 0.10.6
Summary: Agentic Workflows Made Simple
Author-email: Dapr Authors <dapr@dapr.io>
License:                                  Apache License
Project-URL: Documentation, https://github.com/dapr/docs
Project-URL: Source, https://github.com/dapr/python-sdk
Keywords: dapr,agents,workflows
Classifier: Development Status :: 2 - Pre-Alpha
Classifier: Intended Audience :: Developers
Classifier: License :: OSI Approved :: Apache Software License
Classifier: Operating System :: OS Independent
Classifier: Programming Language :: Python
Classifier: Programming Language :: Python :: 3.10
Classifier: Programming Language :: Python :: 3.11
Classifier: Programming Language :: Python :: 3.12
Classifier: Programming Language :: Python :: 3.13
Requires-Python: <3.14,>=3.11
License-File: LICENSE
Requires-Dist: dapr>=1.16.0rc2
Requires-Dist: dapr-ext-fastapi>=1.16.0rc2
Requires-Dist: dapr-ext-workflow>=1.16.0rc2
Requires-Dist: durabletask-dapr>=0.2.0a14
Requires-Dist: pydantic<3.0.0,>=2.11.3
Requires-Dist: jinja2<4.0.0,>=3.1.0
Requires-Dist: pyyaml<7.0.0,>=6.0.1
Requires-Dist: requests<3.0.0,>=2.32.4
Requires-Dist: openapi-pydantic<0.6.0,>=0.5.0
Requires-Dist: rich<14.0.0,>=13.9.4
Requires-Dist: openai<3.0.0,>=1.75.0
Requires-Dist: azure-identity<2.0.0,>=1.21.0
Requires-Dist: huggingface_hub<1.0.0,>=0.33.4
Requires-Dist: colorama<1.0.0,>=0.4.6
Requires-Dist: regex<2026.0.0,>=2023.0.0
Requires-Dist: fastapi<1.0.0,>=0.110.0
Requires-Dist: uvicorn<1.0.0,>=0.27.0
Requires-Dist: aiohttp<4.0.0,>=3.9.0
Requires-Dist: cloudevents<2.0.0,>=1.11.0
Requires-Dist: numpy<3.0.0,>=2.2.2
Requires-Dist: mcp<2.0.0,>=1.20.0
Requires-Dist: websockets<16.0.0,>=15.0.0
Requires-Dist: python-dotenv<2.0.0,>=1.1.1
Requires-Dist: posthog<8.0.0
Requires-Dist: protobuf<7.0.0,>=6.31.0
Requires-Dist: docker>=7.1.0
Requires-Dist: toolbox-core>=0.5.3
Requires-Dist: opentelemetry-api<2.0.0,>=1.35.0
Requires-Dist: opentelemetry-exporter-otlp<2.0.0,>=1.35.0
Requires-Dist: opentelemetry-proto<2.0.0,>=1.35.0
Requires-Dist: opentelemetry-instrumentation-requests>=0.60b0
Requires-Dist: opentelemetry-instrumentation-grpc>=0.60b0
Requires-Dist: wrapt<2.0.0,>=1.14.0
Requires-Dist: openinference-instrumentation<1.0.0,>=0.1.0
Requires-Dist: openinference-semantic-conventions<1.0.0,>=0.1.0
Requires-Dist: opentelemetry.exporter.zipkin.json>=1.39.1
Provides-Extra: test
Requires-Dist: pytest<8.0.0,>=7.0.0; extra == "test"
Requires-Dist: pytest-asyncio<1.0.0,>=0.23.0; extra == "test"
Requires-Dist: pytest-cov<8.0.0,>=4.1.0; extra == "test"
Requires-Dist: pytest-mock<4.0.0,>=3.12.0; extra == "test"
Requires-Dist: pytest-xdist<4.0.0,>=3.0.0; extra == "test"
Requires-Dist: httpx<1.0.0,>=0.27.0; extra == "test"
Requires-Dist: pytest-timeout<3.0.0,>=2.3.0; extra == "test"
Requires-Dist: docker<8.0.0,>=7.0.0; extra == "test"
Provides-Extra: dev
Requires-Dist: mypy<2.0.0,>=1.15.0; extra == "dev"
Requires-Dist: tox<5.0.0,>=4.0.0; extra == "dev"
Requires-Dist: pip-tools<8.0.0,>=7.4.1; extra == "dev"
Requires-Dist: cachetools<7.0.0,>=6.1.0; extra == "dev"
Provides-Extra: vectorstore
Requires-Dist: torch>=2.7.0; extra == "vectorstore"
Requires-Dist: sentence-transformers<5.0.0,>=4.1.0; extra == "vectorstore"
Requires-Dist: chromadb<2.0.0,>=0.4.22; extra == "vectorstore"
Requires-Dist: nltk<4.0.0,>=3.8.0; extra == "vectorstore"
Dynamic: license-file
